{
  "errCode": 0,
  "errMsg": "Success",
  "data": {
    "id": 1939,
    "ts": 1607997218115,
    "mode": 1,
    "tagName": "现场巡检表1报告",
    "storeId": "mEcMpDdb5irT",
    "storeName": "高新2店",
    "submitter": "ZK7M2aDrgFVM",
    "submitterName": "高新督导",
    "status": 1,
    "comment": "本次巡检各项良好",
    "groups": [
      {
        "groupId": 1184,
        "groupName": "評級項目",
        "groupType": 0,
        "items": [
          {
            "id": 20182,
            "subject": "門市活動或行銷製作物、陳列物品與總部要求不符",
            "description": "門市活動或行銷製作物、陳列物品、未經過申請同意即自行張貼舉辦或總公司公告之當期行銷活動未落實宣導",
            "grade": 1,
            "itemScore": 10,
            "comment": "测试通过 pass 一二三四五六七八九十 一二三四五六七八九十 一二三四五六七八九十 一二三四五六七八九十 一二三四五六七八九十 一二三四五六七八九十 一二三四五六七八九十 一二三四五六七八九十 一二三四五六七八九",
            "attachment": [
              {
                "deviceId": -1,
                "mediaType": 0,
                "url": "http://viumo-n3azju2aknpw.oss-cn-beijing.aliyuncs.com/audio/20201215/inspect_091340_PYWGyUmb3Bdg_3146_0.aac"
              },
              {
                "deviceId": -1,
                "mediaType": 2,
                "url": "http://viumo-n3azju2aknpw.oss-cn-beijing.aliyuncs.com/image/20201215/inspect_091340_PYWGyUmb3Bdg_3146_1.jpg"
              },
              {
                "deviceId": -1,
                "mediaType": 1,
                "url": "http://viumo-n3azju2aknpw.oss-cn-beijing.aliyuncs.com/video/20201215/inspect_091340_PYWGyUmb3Bdg_3146_2.mp4"
              },
              {
                "deviceId": -1,
                "mediaType": 2,
                "url": "http://viumo-n3azju2aknpw.oss-cn-beijing.aliyuncs.com/image/20201215/inspect_091340_PYWGyUmb3Bdg_3146_3.jpg"
              }
            ]
          },
          {
            "id": 20183,
            "subject": "擅自更換飲品價格販售或自行給予折扣優惠",
            "description": null,
            "grade": 1,
            "itemScore": 10,
            "comment": "",
            "attachment": []
          },
          {
            "id": 20184,
            "subject": "門市人員因服務態度差，顧客投訴超過2次",
            "description": "門市人員因服務態度不佳，當月發生顧客客訴至總公司二次，經查證屬實者即可開罰",
            "grade": 1,
            "itemScore": 10,
            "comment": "",
            "attachment": []
          },
          {
            "id": 20185,
            "subject": "門市人員儀容儀表不符合規範",
            "description": "門市人員未穿著制服，頭髮過肩要綁，不可做美甲，無配手飾、垂釣飾耳環、無著花俏外套破褲",
            "grade": 1,
            "itemScore": 10,
            "comment": "",
            "attachment": []
          },
          {
            "id": 20186,
            "subject": "銷售產品不合規",
            "description": "銷售產品未經過SOP操作，自行更改比例表或操作方式：或使用非總公司原物料，自行購買非總公司之產品（立即開罰）",
            "grade": -1,
            "itemScore": 10,
            "comment": "",
            "attachment": []
          },
          {
            "id": 20187,
            "subject": "販賣過期原物料、私自變更原物料製造日或到期日",
            "description": null,
            "grade": 1,
            "itemScore": 10,
            "comment": "",
            "attachment": []
          }
        ]
      },
      {
        "groupId": 1185,
        "groupName": "門店形象",
        "groupType": 1,
        "items": [
          {
            "id": 20188,
            "subject": "整體環境乾凈，整齊，無明顯雜物",
            "description": "地面、操作間、收銀臺及衛生死角等工作區域是否清潔，無雜物",
            "grade": 10,
            "itemScore": 10,
            "comment": "",
            "attachment": []
          }
        ]
      },
      {
        "groupId": 1186,
        "groupName": "員工形象",
        "groupType": 1,
        "items": [
          {
            "id": 20189,
            "subject": "精神狀態良好，能夠主動提供服務",
            "description": "員工的精神狀態良好，對顧客微笑，主動向顧客提供服務",
            "grade": 10,
            "itemScore": 10,
            "comment": "",
            "attachment": []
          },
          {
            "id": 20190,
            "subject": "服裝儀容符合公司規定",
            "description": "髮型、指甲、個人衛生符合公司規定，並保持整潔與淡妝的狀態",
            "grade": 10,
            "itemScore": 10,
            "comment": "",
            "attachment": []
          }
        ]
      },
      {
        "groupId": 1187,
        "groupName": "衛生環境",
        "groupType": 1,
        "items": [
          {
            "id": 20191,
            "subject": "走道乾凈整齊，無堆放雜物現象",
            "description": "店內各走道乾凈整潔，無堆放雜物，無擁堵現象",
            "grade": 10,
            "itemScore": 10,
            "comment": "",
            "attachment": []
          },
          {
            "id": 20192,
            "subject": "操作臺擺放整齊，無私人用品",
            "description": "操作臺工具擺放整齊，無私人用品，工具使用完畢之後正確歸位",
            "grade": 10,
            "itemScore": 10,
            "comment": "",
            "attachment": []
          }
        ]
      },
      {
        "groupId": 1188,
        "groupName": "設備檢查",
        "groupType": 1,
        "items": [
          {
            "id": 20193,
            "subject": "設備按時清洗，保持潔凈",
            "description": "員工根據客流情況，清洗必要的設備，保持設備乾凈整潔",
            "grade": 10,
            "itemScore": 10,
            "comment": "",
            "attachment": []
          }
        ]
      },
      {
        "groupId": 1189,
        "groupName": "服務",
        "groupType": 1,
        "items": [
          {
            "id": 20194,
            "subject": "標準三聲問候服務，迎客，詢問，送客",
            "description": "標準的迎客聲、詢問聲、送客聲",
            "grade": 10,
            "itemScore": 10,
            "comment": "",
            "attachment": []
          }
        ]
      },
      {
        "groupId": 1190,
        "groupName": "附加評分項目",
        "groupType": 2,
        "items": [
          {
            "id": 20195,
            "subject": "門市人员上班配戴名牌",
            "description": "对于达成者（合格），不加分；对于未達成者（不合格）扣20分",
            "grade": 1,
            "itemScore": -20,
            "comment": "",
            "attachment": []
          },
          {
            "id": 20196,
            "subject": "總部公告、比例表更新、區组會議宣達資訊正确傳達，列印公告宣導，門市伙伴閱讀签名",
            "description": "对于达成者（合格），不加分；对于其中未達成者（不合格）扣20分",
            "grade": 1,
            "itemScore": -20,
            "comment": "",
            "attachment": []
          },
          {
            "id": 20197,
            "subject": "每店需由二名煮茶、服務認證的人員，共4名，檢查是否滿足要求（一）",
            "description": "对于4名人员达成者（合格），不加分；对于未達成者一位（不合格）扣5分",
            "grade": 1,
            "itemScore": -5,
            "comment": "",
            "attachment": []
          },
          {
            "id": 20198,
            "subject": "每店需由二名煮茶、服務認證的人員，共4名，檢查是否滿足要求（二）",
            "description": "对于4名人员达成者（合格），不加分；对于未達成者一位（不合格）扣6分",
            "grade": -1,
            "itemScore": -5,
            "comment": "",
            "attachment": []
          },
          {
            "id": 20199,
            "subject": "每店需由二名煮茶、服務認證的人員，共4名，檢查是否滿足要求（三）",
            "description": "对于4名人员达成者（合格），不加分；对于未達成者一位（不合格）扣7分",
            "grade": 1,
            "itemScore": -5,
            "comment": "",
            "attachment": []
          },
          {
            "id": 20200,
            "subject": "每店需由二名煮茶、服務認證的人員，共4名，檢查是否滿足要求（四）",
            "description": "对于4名人员达成者（合格），不加分；对于未達成者一位（不合格）扣8分",
            "grade": -1,
            "itemScore": -5,
            "comment": "",
            "attachment": []
          },
          {
            "id": 20201,
            "subject": "整體環境乾凈，整齊，無明顯雜物",
            "description": "三次檢測優秀（合格），加5分；未達成者（不合格），不减分",
            "grade": 1,
            "itemScore": 5,
            "comment": "",
            "attachment": []
          }
        ]
      },
      {
        "groupId": 1191,
        "groupName": "合格率评估项1",
        "groupType": 0,
        "items": [
          {
            "id": 20202,
            "subject": "新增巡检类别",
            "description": "",
            "grade": 1,
            "itemScore": 10,
            "comment": "",
            "attachment": []
          }
        ]
      },
      {
        "groupId": 1192,
        "groupName": "合格率评估项2",
        "groupType": 0,
        "items": [
          {
            "id": 20203,
            "subject": "合格率评估项",
            "description": "",
            "grade": 1,
            "itemScore": 10,
            "comment": "",
            "attachment": []
          }
        ]
      },
      {
        "groupId": 1193,
        "groupName": "合格率评估项3",
        "groupType": 0,
        "items": [
          {
            "id": 20204,
            "subject": "合格率评估项",
            "description": "",
            "grade": 1,
            "itemScore": 10,
            "comment": "",
            "attachment": []
          }
        ]
      },
      {
        "groupId": 1194,
        "groupName": "合格率评估项4",
        "groupType": 0,
        "items": [
          {
            "id": 20205,
            "subject": "合格率评估项",
            "description": "",
            "grade": 1,
            "itemScore": 10,
            "comment": "",
            "attachment": []
          }
        ]
      },
      {
        "groupId": 1195,
        "groupName": "合格率评估项5",
        "groupType": 0,
        "items": [
          {
            "id": 20206,
            "subject": "合格率评估项",
            "description": "",
            "grade": 1,
            "itemScore": 10,
            "comment": "",
            "attachment": []
          }
        ]
      },
      {
        "groupId": 1196,
        "groupName": "合格率评估项6",
        "groupType": 0,
        "items": [
          {
            "id": 20207,
            "subject": "合格率评估项",
            "description": "",
            "grade": 1,
            "itemScore": 10,
            "comment": "",
            "attachment": []
          }
        ]
      },
      {
        "groupId": 1197,
        "groupName": "合格率评估项7",
        "groupType": 0,
        "items": [
          {
            "id": 20208,
            "subject": "合格率评估项",
            "description": "",
            "grade": 1,
            "itemScore": 10,
            "comment": "",
            "attachment": []
          }
        ]
      }
    ],
    "feedbacks": [
      {
        "attachment": [
          {
            "deviceId": -1,
            "mediaType": 0,
            "url": "http://viumo-n3azju2aknpw.oss-cn-beijing.aliyuncs.com/audio/20201215/inspect_095338_mEcMpDdb5irT_-1_0.aac"
          },
          {
            "deviceId": -1,
            "mediaType": 1,
            "url": "http://viumo-n3azju2aknpw.oss-cn-beijing.aliyuncs.com/video/20201215/inspect_095338_mEcMpDdb5irT_-1_1.mp4"
          },
          {
            "deviceId": -1,
            "mediaType": 2,
            "url": "http://viumo-n3azju2aknpw.oss-cn-beijing.aliyuncs.com/image/20201215/inspect_095338_mEcMpDdb5irT_-1_2.jpg"
          },
          {
            "deviceId": -1,
            "mediaType": 1,
            "url": "http://viumo-n3azju2aknpw.oss-cn-beijing.aliyuncs.com/video/20201215/inspect_095338_mEcMpDdb5irT_-1_3.mp4"
          },
          {
            "deviceId": -1,
            "mediaType": 2,
            "url": "http://viumo-n3azju2aknpw.oss-cn-beijing.aliyuncs.com/image/20201215/inspect_095338_mEcMpDdb5irT_-1_4.jpg"
          }
        ],
        "ts": 1607997218115,
        "subject": "Android现场巡检问题反馈",
        "description": "测试通过\npass\n一二三四五六七八九十\n一二三四五六七八九十\n一二三四五六七八九十\n一二三四五六七八九十\n一二三四五六七八九十\n一二三四五六七八九十\n一二三四五六七八九十\n一二三四五六七八九十\n一二三四五六七八九"
      },
      {
        "attachment": [],
        "ts": 1607997218115,
        "subject": "Android现场巡检问题反馈名称为空",
        "description": "测试通过\npass\n一二三四五六七八九十\n一二三四五六七八九十\n一二三四五六七八九十\n一二三四五六七八九十\n一二三四五六七八九十\n一二三四五六七八九十\n一二三四五六七八九十\n一二三四五六七八九十\n一二三四五六七八九"
      },
      {
        "attachment": [
          {
            "deviceId": -1,
            "mediaType": 1,
            "url": "http://viumo-n3azju2aknpw.oss-cn-beijing.aliyuncs.com/video/20201215/inspect_095338_mEcMpDdb5irT_-1_5.mp4"
          }
        ],
        "ts": 1607997218115,
        "subject": "Android现场巡检问题反馈测试",
        "description": "测试通过\npass\n一二三四五六七八九十\n一二三四五六七八九十\n一二三四五六七八九十\n一二三四五六七八九十\n一二三四五六七八九十\n一二三四五六七八九十"
      }
    ],
    "signature": {
      "type": 2,
      "content": "http://viumo-n3azju2aknpw.oss-cn-beijing.aliyuncs.com/image/20201215/inspect_095338_mEcMpDdb5irT_5.jpg"
    }
  }
}